rtl/baud_gen.v
`timescale 1ns / 1ps

module baud_gen #(

    parameter integer DIVISOR = 27
)(

    input wire clk,
    input wire rst_n,
    output reg tick
);
reg [15:0] count;

always @(posedge clk) begin
    if (!rst_n) begin
        count <= 16'd0;
        tick <= 1'b0;
    end else if (count == DIVISOR -1) begin
        count <= 16'd0 ;
        tick <= 1'b1;
    end else begin
        count <= count + 1'b1;
        tick <= 1'b0;
    end
end

endmodule

sim/waves.vcd
$date
	Fri Jul 31 04:46:30 2026
$end
$version
	Icarus Verilog
$end
$timescale
	1ps
$end
$scope module baud_gen $end
$var wire 1 ! clk $end
$var wire 1 " rst_n $end
$var parameter 32 # DIVISOR $end
$var reg 16 $ count [15:0] $end
$var reg 1 % tick $end
$upscope $end
$scope module dump $end
$upscope $end
$enddefinitions $end
$comment Show the parameter values. $end
$dumpall
b100 #
$end
#0
$dumpvars
0%
b0 $
0"
1!
$end
#10000
0!
#20000
1"
1!
#30000
0!
#40000
b1 $
1!
#50000
0!
#60000
b10 $
1!
#70000
0!
#80000
b11 $
1!
#90000
0!
#100000
1%
b0 $
1!
#110000
0!
#120000
0%
b1 $
1!
#130000
0!
#140000
b10 $
1!
#150000
0!
#160000
b11 $
1!
#170000
0!
#180000
1%
b0 $
1!
